nexus_proto/__init__.py
keeps_learn_nexus_proto-0.7.0.dist-info/METADATA
keeps_learn_nexus_proto-0.7.0.dist-info/WHEEL
keeps_learn_nexus_proto-0.7.0.dist-info/top_level.txt
keeps_learn_nexus_proto-0.7.0.dist-info/RECORD
