Metadata-Version: 2.4
Name: keeps-learn-nexus-proto
Version: 0.7.0
Summary: Shared Protocol Buffer definitions for Nexus microservices
Author-email: Keeps <tecnologia@keeps.com.br>
License: MIT
Project-URL: Homepage, https://github.com/Keeps-Learn/nexus-proto
Project-URL: Repository, https://github.com/Keeps-Learn/nexus-proto.git
Project-URL: Issues, https://github.com/Keeps-Learn/nexus-proto/issues
Keywords: grpc,protobuf,proto,microservices
Classifier: Development Status :: 4 - Beta
Classifier: Intended Audience :: Developers
Classifier: License :: OSI Approved :: MIT License
Classifier: Programming Language :: Python :: 3
Classifier: Topic :: Software Development :: Libraries
Classifier: Topic :: Communications
Requires-Python: >=3.7
